pyweath/__init__.py
pyweath/__main__.py
pyweath/pyweath.py
pyweath-1.0.2.dist-info/LICENSE
pyweath-1.0.2.dist-info/METADATA
pyweath-1.0.2.dist-info/WHEEL
pyweath-1.0.2.dist-info/entry_points.txt
pyweath-1.0.2.dist-info/top_level.txt
pyweath-1.0.2.dist-info/RECORD
