Metadata-Version: 2.1
Name: pyweath
Version: 1.0.2
Summary: A simple weather library for Python.
Author-email: Jean Luis Adrover <ja4146@nyu.edu>, "Harry (Sang In) Kang" <sik247@nyu.edu>
License: GNU GENERAL PUBLIC LICENSE
Project-URL: Homepage, https://github.com/software-students-spring2024/3-python-package-exercise-team-pyday
Keywords: weather,temperature,forecast,air quality,owm
Requires-Python: >=3.11
License-File: LICENSE
Provides-Extra: dev
Requires-Dist: pytest ; extra == 'dev'
